{
    "Dairesi": "2.Ceza Dairesi",
    "Mahkemesi": "Asliye Ceza Mahkemesi",
    "Mahkeme Günü": "25",
    "Mahkeme Ayı": "01",
    "Mahkeme Yılı": "2021",
    "Suç": " Mala zarar verme, kişilerin huzur ve sükununu bozma",
    "Dosyanın Daireye Geliş Günü": "",
    "Dosyanın Daireye Geliş Ayı": "",
    "Dosyanın Daireye Geliş Yılı": "",
    "Kanun Yolu": "",
    "Temyiz Eden": "",
    "Dava Türü": "",
    "Birinci Mahkemesi": "",
    "ictihat": "   HÜKÜM: Mahkumiyet    Dosya incelenerek gereği düşünüldü;  5237 sayılı TCK'nın 53. maddesinin bazı bölümlerinin iptaline ilişkin Anayasa Mahkemesinin 24.11.2015 tarihinde yürürlüğe giren 08.10.2015 gün ve 2014/140 E., 2015/85 K. sayılı kararı da nazara alınarak bu maddede öngörülen hak yoksunluklarının uygulanmasının infaz aşamasında gözetilmesi mümkün görülmüş, dosya içeriğine göre diğer temyiz itirazları yerinde görülmemiştir. Ancak;  1. Sanık hakkında 5237 sayılı TCK’nın 123/1. maddesi uyarınca kişilerin huzur ve sükununu bozma ve TCK’nin 151/1. maddesi uyarınca mala zarar verme suçlarından hükümler kurulduğu, suç tarihinde mala zarar verme suçunun uzlaşma kapsamında bulunmaması ve 5271 sayılı CMK’nin 253/3. maddesi uyarınca uzlaştırma kapsamına giren bir suçun, bu kapsamına girmeyen bir başka suçla işlenmiş olması nedeniyle uzlaştırmanın mümkün olmadığı anlaşılmış ise de, TCK’nın 151/1. maddesi kapsamındaki mala zarar verme suçunun 02.12.2016 tarihli Resmi Gazete'de yayımlanarak aynı tarihte yürürlüğe giren 6763 sayılı Kanun'un 34. maddesiyle değişik 5271 sayılı CMK'nın 253. maddesi ve maddeye eklenen fıkraya göre uzlaşma kapsamına alındığı, bu nedenle CMK’nın 253/3. maddesinin uygulanma koşullarının ortadan kalktığı, sanık ile katılan arasında söz konusu kanun değişikliğine göre, kişilerin huzur ve sükununu bozma ve mala zarar verme suçları yönünden uzlaştırma işlemi uygulanıp sonucuna göre sanığın hukuki durumunun değerlendirilmesinde zorunluluk bulunması,  2. Kabule göre de;  Adli sicil kaydında yer alan ve tekerrüre esas olan en ağır cezaya ilişkin İstanbul Anadolu 2. Ağır Ceza Mahkemesinin 2010/138 Esas, 2011/420 Karar sayılı ilamındaki, TCK 81/1. maddesi kapsamında 7 yıl 6 ay hapis cezasının tekerrüre esas alınması gerektiği gözetilmeden, birden fazla hükümlülüğün tekerrüre esas alınması suretiyle yazılı şekilde hüküm kurulması,  Bozmayı gerektirmiş, sanığın temyiz itirazları bu itibarla yerinde görülmüş olduğundan hükümlerin bu sebepten dolayı istem gibi BOZULMASINA, 25.01.2021 gününde oy birliğiyle karar verildi."
}