{
    "Dairesi": "6.Ceza Dairesi",
    "Mahkemesi": "Asliye Ceza Mahkemesi",
    "Mahkeme Günü": "25",
    "Mahkeme Ayı": "01",
    "Mahkeme Yılı": "2021",
    "Suç": " Kamu malına zarar verme",
    "Dosyanın Daireye Geliş Günü": "",
    "Dosyanın Daireye Geliş Ayı": "",
    "Dosyanın Daireye Geliş Yılı": "",
    "Kanun Yolu": "",
    "Temyiz Eden": "",
    "Dava Türü": "",
    "Birinci Mahkemesi": "",
    "ictihat": "   HÜKÜM : Beraat    Mahalli mahkemece verilen hüküm temyiz edilmekle dosya incelenerek, gereği düşünüldü:  Hüküm fıkrasına 5271 sayılı CMK’nın 223/2-c maddesi gereğince beraatine yazılması gerekirken, yazılı şekilde uygulama yapılması,  Bozmayı gerektirmiş, katılan vekilinin temyiz itirazı bu bakımdan yerinde görülmüş olduğundan, hükmün açıklanan nedenlerle tebliğnameye aykırı olarak BOZULMASINA, bozma nedeni yeniden yargılama yapılmasını gerektirmediğinden, 5320 sayılı Yasa'nın 8/1. maddesi aracılığıyla 1412 sayılı CMUK'un 322. maddesinin verdiği yetkiye dayanılarak, hüküm fıkrasına \"sanığın üzerine atılı suç açısından\" cümlesinden sonra gelmek üzere \"5271 sayılı CMK'nın 223/2-c maddesi gereğince Beraatine\" tümcesinin eklenmesi suretiyle, diğer yönleri usul ve yasaya uygun bulunan hükmün DÜZELTİLEREK ONANMASINA, 25/01/2021 gününde oy birliğiyle karar verildi."
}