{
    "Dairesi": "4.Ceza Dairesi",
    "Mahkemesi": "Asliye Ceza Mahkemesi",
    "Mahkeme Günü": "13",
    "Mahkeme Ayı": "01",
    "Mahkeme Yılı": "2021",
    "Suç": " Hakaret",
    "Dosyanın Daireye Geliş Günü": "",
    "Dosyanın Daireye Geliş Ayı": "",
    "Dosyanın Daireye Geliş Yılı": "",
    "Kanun Yolu": "",
    "Temyiz Eden": "",
    "Dava Türü": "",
    "Birinci Mahkemesi": "",
    "ictihat": "   HÜKÜM : Beraat       Yerel Mahkemece verilen hüküm temyiz edilmekle, başvurunun süresi ve kararın niteliği ile suç tarihine göre dosya görüşüldü:  UYAP'tan alınan güncel nüfus kaydına göre temyiz talebinde bulunan katılanın 17/04/2018 tarihinde öldüğü, CMK'nın 243. maddesi gereğince katılma kararının hükümsüz kaldığı, ölenin mirasçılarına, katılanın haklarını takip etmek üzere yapılan tebligata rağmen, mirasçıların temyiz yoluna başvurmadıkları,  Anlaşıldığından, 5320 sayılı Kanunun 8/1 ve 1412 sayılı CMUK'nın 317. maddeleri uyarınca ölen katılan ...’in TEMYİZ İSTEĞİNİN REDDİNE, 13/01/2021 tarihinde oy birliğiyle karar verildi."
}