{
    "Dairesi": "8.Ceza Dairesi",
    "Mahkemesi": "Asliye Ceza Mahkemesi",
    "Mahkeme Günü": "13",
    "Mahkeme Ayı": "01",
    "Mahkeme Yılı": "2021",
    "Suç": " Hakkı olmayan yere tecavüz etme",
    "Dosyanın Daireye Geliş Günü": "",
    "Dosyanın Daireye Geliş Ayı": "",
    "Dosyanın Daireye Geliş Yılı": "",
    "Kanun Yolu": "",
    "Temyiz Eden": "",
    "Dava Türü": "",
    "Birinci Mahkemesi": "",
    "ictihat": "   HÜKÜM : Mahkumiyet    Gereği görüşülüp düşünüldü:  Bozmaya uyularak; yapılan yargılamaya, dosya içeriğine, toplanıp karar yerinde gösterilen ve değerlendirilen delillere, oluşa ve mahkemenin soruşturma sonucunda oluşan inanç ve taktirine göre sair temyiz itirazlarının reddine, ancak;  Ceza Genel Kurulu'nun 03.04.2018 tarih ve 2017/853 Esas, 2018/135 Karar sayılı ilamı ve 09.02.2016 tarih ve 2014/71 Esas, 2016/42 Karar sayılı ilamı da gözetildiğinde; bozmadan önce verilen ve yalnızca sanık tarafından temyiz edilen Torul Asliye Ceza Mahkemesinin 18.11.2014 tarihli kararı ile hükmedilen hapis cezasının TCK.nın 50/1-d maddesi uyarınca tedbire çevrildiği ve aleyhe temyiz olmadığı, CMUK.nın 326/son madde ve fıkrası uyarınca sanık lehine kazanılmış hak oluşması nedeniyle, son hükümde verilen hapis cezasının tedbire çevrilmesi gerektiği gözetilmeden yazılı şekilde karar verilmesi,  Yasaya aykırı, sanık müdafinin temyiz itirazı bu itibarla yerinde görülmüş olduğundan hükmün bu sebepten dolayı 5320 sayılı Yasanın 8/1. maddesi uyarınca uygulanması gereken CMUK.nın 321. maddesi gereğince BOZULMASINA, 13.01.2021 gününde oybirliğiyle karar verildi."
}