{
    "Dairesi": "10.Ceza Dairesi",
    "Mahkemesi": "",
    "Mahkeme Günü": "14",
    "Mahkeme Ayı": "01",
    "Mahkeme Yılı": "2021",
    "Suç": " Kullanmak için uyuşturucu madde bulundurma",
    "Dosyanın Daireye Geliş Günü": "",
    "Dosyanın Daireye Geliş Ayı": "",
    "Dosyanın Daireye Geliş Yılı": "",
    "Kanun Yolu": "",
    "Temyiz Eden": "",
    "Dava Türü": "",
    "Birinci Mahkemesi": "",
    "ictihat": " Mahkeme : ELAZIĞ Çocuk Mahkemesi   Hüküm : Tedavi ve denetimli serbestlik tedbirine uyulmaması üzerine mahkûmiyet    Dosya incelendi.  GEREĞİ GÖRÜŞÜLÜP DÜŞÜNÜLDÜ :  1-Gerekçeli karar başlığında suç tarihinin \"28/10/2014\" yerine \"31/03/2015\" olarak yazılması,  2- Kullanmak için uyuşturucu madde bulundurma suçundan dolayı başlatılan soruşturmada TCK'nın 191. maddesinin 2. fıkrası uyarınca verilen kamu davasının açılmasının ertelenmesi kararının sanığa usulüne uygun tebliğ edildiğine dair belgenin dosya içerisinde ve UYAP sisteminde denetime açık bir şekilde bulundurulması gerektiğinin gözetilmemesi,  Bozmayı gerektirmiş, sanık ve müdafiinin temyiz itirazları bu nedenle yerinde olduğundan, hükmün BOZULMASINA, 14/01/2021 tarihinde oy birliği ile karar verildi."
}