{
    "Dairesi": "17.Hukuk Dairesi",
    "Mahkemesi": "Ticaret Mahkemesi",
    "Mahkeme Günü": "21",
    "Mahkeme Ayı": "01",
    "Mahkeme Yılı": "2021",
    "Suç": "",
    "Dosyanın Daireye Geliş Günü": "",
    "Dosyanın Daireye Geliş Ayı": "",
    "Dosyanın Daireye Geliş Yılı": "",
    "Kanun Yolu": "",
    "Temyiz Eden": "",
    "Dava Türü": "",
    "Birinci Mahkemesi": "",
    "ictihat": "    Taraflar arasındaki uyuşmazlık hakem heyeti kararına yapılan ititazın sonunda itirazın kısmen kabulüne dair verilen itiraz hakem heyetinin 2019/İHK-4258 sayılı ve 24.04.2019 günlü kararının süresi içinde davalı vekili tarafından temyiz edilmesi üzerine dosya incelendi, gereği düşünüldü:       5684 sayılı Sigortacılık Yasasının 30/12. maddesi gereği sigorta tahkim komisyonlarının 40.000,00 TL'yi geçmeyen kararları kesindir. Kesin olan kararların temyiz istemleri hakkında mahkemece bir karar verilebileceği gibi, 1.6.1990 gün 3/4 sayılı İçtihadı Birleştirme Kararı uyarınca Yargıtay’ca da temyiz isteminin reddine karar verilebilir. Uyuşmazlık Hakem Heyeti; başvuranların taleplerinin kısmen kabulü ile başvuran için 2.470,37 TL'nin davalıdan tahsiline karar verdiğine göre 40.000,00 TL'lik kesinlik sınırı olduğundan, bu sebeple başvuran lehine kabul edilen manevi tazminat miktarları itibariyle karar kesin niteliktedir. Davalı yönünden temyiz isteminin miktar yönünden reddine karar vermek gerekmiştir.  SONUÇ: Yukarıda açıklanan nedenlerle davalı vekilinin temyiz dilekçesinin itiraz hakem heyeti kararının kesin olması nedeniyle REDDİNE, peşin alınan harcın istek halinde temyiz eden davalıya geri verilmesine 21/01/2021 gününde oybirliğiyle karar verildi."
}